{
  "roadmap": {
    "tasks": [
      {
        "step_id": "step_1",
        "name": "Tách văn bản thành câu và nhóm chunk",
        "description": "Tách văn bản gốc tiếng Việt thành các câu, sau đó nhóm chúng lại thành chunks phù hợp với thông tin cần tóm tắt.",
        "tool": "sent_tokenize; chunk_text"
      },
      {
        "step_id": "step_2",
        "name": "Xác định ý chính trong mỗi chunk",
        "description": "Phân tích từng chunk để xác định các ý chính và giữ lại những thông tin quan trọng.",
        "tool": "summarize_chunk; refine_summary"
      },
      {
        "step_id": "step_3",
        "name": "Gộp bản tóm tắt của mỗi chunk thành một bản tổng hợp",
        "description": "Tổng hợp các bản tóm tắt từ từng chunk để tạo ra bản tóm tắt cuối cùng.",
        "tool": "merge_summaries"
      },
      {
        "step_id": "step_4",
        "name": "Refine và kiểm chứng thông tin tổng quan",
        "description": "Tinh chỉnh văn phong cho bản tổng hợp, đồng thời kiểm tra lại các thông tin chính để đảm bảo không thay đổi entity.",
        "tool": "refine_summary; verify_claim"
      }
    ],
    "total_steps": 4,
    "notes": "Bắt đầu từ bước tách và nhóm chunk đến cuối cùng là refinement và verification, mỗi bước đều cần có output cụ thể."
  }
}