{
  "session_id": "c9694487",
  "current_phase": "execution",
  "iteration_count": 1,
  "roadmap_version": "v1",
  "last_decision": "finalize",
  "confidence_score": 0.85,
  "style": "news_brief",
  "input_word_count": 537,
  "created_at": "2026-03-27T20:02:23.576274",
  "history": [
    {
      "agent": "planner",
      "action": "create_roadmap",
      "timestamp": "2026-03-27T20:03:34.459995",
      "result_summary": "Roadmap v1 created",
      "details": {
        "version": "v1"
      }
    },
    {
      "agent": "planner_observation",
      "action": "analyze_roadmap",
      "timestamp": "2026-03-27T20:04:31.254595",
      "result_summary": "Observation for v1 complete"
    },
    {
      "agent": "planner_reflection",
      "action": "evaluate_roadmap",
      "timestamp": "2026-03-27T20:04:56.772976",
      "result_summary": "Decision: finalize (confidence: 0.85)",
      "details": {
        "reflection": {
          "coverage_score": 0.85,
          "specificity_score": 0.75,
          "hallucination_risk": "low",
          "tool_utilization": "adequate",
          "decision": "finalize",
          "revision_instructions": "",
          "reasoning": "Roadmap đã bao quát hầu hết ý chính của văn bản gốc với coverage score đạt 0.85 và specificity score là 0.75, đồng thời hallucination risk được đánh giá là low. Mặc dù roadmap thiếu bước kiểm chứng mệnh đề với văn bản gốc nhưng không ảnh hưởng đáng kể đến tổng thể."
        }
      }
    },
    {
      "agent": "execution",
      "action": "split_sentences",
      "timestamp": "2026-03-27T20:04:56.775978",
      "result_summary": "Step 1 completed"
    },
    {
      "agent": "execution_observation",
      "action": "analyze_step",
      "timestamp": "2026-03-27T20:05:40.860954",
      "result_summary": "Observation for step 1 complete"
    },
    {
      "agent": "execution_reflection",
      "action": "evaluate_step",
      "timestamp": "2026-03-27T20:06:01.219957",
      "result_summary": "Decision: next_step",
      "details": {
        "reflection": {
          "factual_consistency": 0.9,
          "coverage_completeness": 0.85,
          "redundancy_score": 0.1,
          "length_compliance": true,
          "decision": "next_step",
          "feedback": "",
          "reasoning": "Bước thực thi đã hoàn thành với chất lượng tốt và không chứa thêm thông tin mới so với văn bản gốc, đồng thời đạt mức độ bao quát chấp nhận được. Đây là bước cuối cùng nên tiếp tục tiến trình."
        }
      }
    },
    {
      "agent": "manager",
      "action": "workflow_complete",
      "timestamp": "2026-03-27T20:06:01.228469",
      "result_summary": "Hoàn thành toàn bộ workflow"
    }
  ],
  "data_store": {
    "sentences": [
      {
        "sentence_id": 1,
        "text": "Theo Báo cáo Hạnh phúc Thế giới (World Happiness Report) 2024 của Liên Hợp Quốc công bố hồi tháng 3, Lithuania là quốc gia 'hạnh phúc nhất thế giới dành cho những người dưới 30 tuổi (gen Z)'."
      },
      {
        "sentence_id": 2,
        "text": "Hai nhà sáng tạo nội dung Ammar Kandil và Staffan Taylor đến từ Yes Theory, kênh truyền thông nổi tiếng của Canada, quyết định đến thủ đô Vilnius để tìm hiểu xem liệu báo cáo có nói đúng."
      },
      {
        "sentence_id": 3,
        "text": "Khi hạ cánh xuống Vilnius, Amma và Staffan bắt đầu nói chuyện với người dân địa phương."
      },
      {
        "sentence_id": 4,
        "text": "Hầu hết người trẻ đều đồng ý quốc gia họ đang sống là nơi tốt nhờ 'đồ ăn tuyệt vời, người dân thân thiện, nhiều cơ hội nghề nghiệp và nền kinh tế đang phát triển'."
      },
      {
        "sentence_id": 5,
        "text": "Nhiều người trong số đó cho rằng các khó khăn mà thế hệ trước chịu đựng đã dạy thế hệ trẻ ngày nay cách tận hưởng cuộc sống trong từng khoảnh khắc và 'tìm thấy vẻ đẹp trong những điều giản dị'."
      },
      {
        "sentence_id": 6,
        "text": "Để thu hút nhiều người trẻ đến nói chuyện hơn, Amma và Staffan đã tổ chức một buổi gặp gỡ."
      },
      {
        "sentence_id": 7,
        "text": "Tại sự kiện, những người tham dự lần lượt bày tỏ quan điểm."
      },
      {
        "sentence_id": 8,
        "text": "'Sau một năm sống tại Mỹ, tôi đánh giá cao cuộc sống ở Lithuania vì tính kết nối với thiên nhiên', một thanh niên chia sẻ."
      },
      {
        "sentence_id": 9,
        "text": "Người này nói thêm du khách có thể dễ dàng tiếp cận một hồ nước hay khu rừng tại Lithuania và chiêm ngưỡng khung cảnh thiên nhiên tuyệt đẹp ở đó."
      },
      {
        "sentence_id": 10,
        "text": "'Lithuania chưa bao giờ tốt như hiện nay', một phụ nữ trẻ khác thừa nhận."
      },
      {
        "sentence_id": 11,
        "text": "Khi nói về hạnh phúc, một người dân địa phương cho biết dù người trẻ sống ở đất nước này 'khá vui vẻ' nhưng không có nghĩa họ không phải đối mặt với nhiều vấn đề, áp lực cuộc sống."
      },
      {
        "sentence_id": 12,
        "text": "Sau buổi gặp gỡ, Ammar và Staffan dành phần còn lại của chuyến đi để giao lưu với người dân địa phương, ghé thăm các điểm du lịch như nhà tù cũ Lukiškės giờ là địa điểm văn hóa và tượng đài Hill of Crosses."
      },
      {
        "sentence_id": 13,
        "text": "'Đây là một trong những trải nghiệm du lịch hạnh phúc nhất tôi từng có', Ammar, người từng đi khắp thế giới, chia sẻ với độc giả trên kênh Yes Theory khi đang tham gia một bữa tiệc tối."
      },
      {
        "sentence_id": 14,
        "text": "Steffan đồng tình khi nhận định Lithuania chắc chắn là một trong những quốc gia cởi mở, hào phóng, tử tế nhất mà anh từng đến."
      },
      {
        "sentence_id": 15,
        "text": "Video của hai du khách đến từ Canada đã thu hút gần một triệu lượt xem và bình luận chỉ sau vài ngày đăng tải."
      },
      {
        "sentence_id": 16,
        "text": "Một người từng đến Vilnius học theo diện trao đổi sinh viên chia sẻ thời gian ở Liathuania là quãng thời gian hạnh phúc nhất của mình."
      },
      {
        "sentence_id": 17,
        "text": "'Cảm ơn Liathuania đã chào đón tôi', người này nói."
      },
      {
        "sentence_id": 18,
        "text": "'Tình yêu, sự sáng tạo và lòng tốt có thể giúp chúng ta vượt qua quá khứ đen tối, biến tiêu cực thành ánh sáng và giúp đỡ người khác', một người dân địa phương bày tỏ sau khi xem video của Ammar và Steffan."
      },
      {
        "sentence_id": 19,
        "text": "Anh Minh(TheoYes Theory, DM)"
      }
    ]
  },
  "stats": {
    "planner_loop": 0,
    "planner_observation_loop": 0,
    "planner_reflection_loop": 0,
    "execution_loop": 0,
    "execution_observation_loop": 0,
    "execution_reflection_loop": 0,
    "chunks": 0
  },
  "input_text": "Theo Báo cáo Hạnh phúc Thế giới (World Happiness Report) 2024 của Liên Hợp Quốc công bố hồi tháng 3, Lithuania là quốc gia 'hạnh phúc nhất thế giới dành cho những người dưới 30 tuổi (gen Z)'. Hai nhà sáng tạo nội dung Ammar Kandil và Staffan Taylor đến từ Yes Theory, kênh truyền thông nổi tiếng của Canada, quyết định đến thủ đô Vilnius để tìm hiểu xem liệu báo cáo có nói đúng. Khi hạ cánh xuống Vilnius, Amma và Staffan bắt đầu nói chuyện với người dân địa phương. Hầu hết người trẻ đều đồng ý quốc gia họ đang sống là nơi tốt nhờ 'đồ ăn tuyệt vời, người dân thân thiện, nhiều cơ hội nghề nghiệp và nền kinh tế đang phát triển'. Nhiều người trong số đó cho rằng các khó khăn mà thế hệ trước chịu đựng đã dạy thế hệ trẻ ngày nay cách tận hưởng cuộc sống trong từng khoảnh khắc và 'tìm thấy vẻ đẹp trong những điều giản dị'. Để thu hút nhiều người trẻ đến nói chuyện hơn, Amma và Staffan đã tổ chức một buổi gặp gỡ. Tại sự kiện, những người tham dự lần lượt bày tỏ quan điểm. 'Sau một năm sống tại Mỹ, tôi đánh giá cao cuộc sống ở Lithuania vì tính kết nối với thiên nhiên', một thanh niên chia sẻ. Người này nói thêm du khách có thể dễ dàng tiếp cận một hồ nước hay khu rừng tại Lithuania và chiêm ngưỡng khung cảnh thiên nhiên tuyệt đẹp ở đó. 'Lithuania chưa bao giờ tốt như hiện nay', một phụ nữ trẻ khác thừa nhận. Khi nói về hạnh phúc, một người dân địa phương cho biết dù người trẻ sống ở đất nước này 'khá vui vẻ' nhưng không có nghĩa họ không phải đối mặt với nhiều vấn đề, áp lực cuộc sống. Sau buổi gặp gỡ, Ammar và Staffan dành phần còn lại của chuyến đi để giao lưu với người dân địa phương, ghé thăm các điểm du lịch như nhà tù cũ Lukiškės giờ là địa điểm văn hóa và tượng đài Hill of Crosses. 'Đây là một trong những trải nghiệm du lịch hạnh phúc nhất tôi từng có', Ammar, người từng đi khắp thế giới, chia sẻ với độc giả trên kênh Yes Theory khi đang tham gia một bữa tiệc tối. Steffan đồng tình khi nhận định Lithuania chắc chắn là một trong những quốc gia cởi mở, hào phóng, tử tế nhất mà anh từng đến. Video của hai du khách đến từ Canada đã thu hút gần một triệu lượt xem và bình luận chỉ sau vài ngày đăng tải. Một người từng đến Vilnius học theo diện trao đổi sinh viên chia sẻ thời gian ở Liathuania là quãng thời gian hạnh phúc nhất của mình. 'Cảm ơn Liathuania đã chào đón tôi', người này nói. 'Tình yêu, sự sáng tạo và lòng tốt có thể giúp chúng ta vượt qua quá khứ đen tối, biến tiêu cực thành ánh sáng và giúp đỡ người khác', một người dân địa phương bày tỏ sau khi xem video của Ammar và Steffan. Anh Minh(TheoYes Theory, DM)",
  "last_updated": "2026-03-27T20:04:56.774978"
}